README.md
setup.cfg
setup.py
bestiapop/__init__.py
bestiapop/__main__.py
bestiapop/bestiapop.py
bestiapop.egg-info/PKG-INFO
bestiapop.egg-info/SOURCES.txt
bestiapop.egg-info/dependency_links.txt
bestiapop.egg-info/requires.txt
bestiapop.egg-info/top_level.txt
bestiapop/common/__init__.py
bestiapop/common/bestiapop_utils.py
bestiapop/connectors/__init__.py
bestiapop/connectors/nasapower_connector.py
bestiapop/connectors/silo_connector.py
bestiapop/producers/__init__.py
bestiapop/producers/output.py