Metadata-Version: 2.1
Name: bestiapop
Version: 3.0.9
Summary: Climate Data Mining Automation Framework
Home-page: https://bestiapop.readthedocs.io/en/latest/
Author: Diego Perez & Jonathan Ojeda
Author-email: darkquasar7@gmail.com
License: bsd-3-clause
Download-URL: https://github.com/JJguri/bestiapop/archive/v3.0.9.tar.gz
Keywords: silo,apsim,nasapower,dssat,met,wth,crop model,crop modelling,crops,agriculture,data science,climate,weather,automation
Platform: UNKNOWN
Classifier: Development Status :: 5 - Production/Stable
Classifier: Intended Audience :: Developers
Classifier: Intended Audience :: Information Technology
Classifier: Intended Audience :: Science/Research
Classifier: License :: OSI Approved :: BSD License
Classifier: Programming Language :: Cython
Classifier: Programming Language :: Python
Classifier: Programming Language :: Python :: 3
Classifier: Programming Language :: Python :: 3.6
Classifier: Programming Language :: Python :: 3.7
Classifier: Programming Language :: Python :: 3.8
Classifier: Topic :: Scientific/Engineering
Classifier: Topic :: Database
Classifier: Topic :: Software Development :: Libraries :: Python Modules
Classifier: Operating System :: Unix
Classifier: Operating System :: POSIX :: Linux
Classifier: Operating System :: MacOS :: MacOS X
Classifier: Operating System :: Microsoft :: Windows
Requires-Python: >=3.6
